tuber/__init__.py
tuber-0.6.0.dist-info/LICENSE
tuber-0.6.0.dist-info/METADATA
tuber-0.6.0.dist-info/WHEEL
tuber-0.6.0.dist-info/top_level.txt
tuber-0.6.0.dist-info/RECORD
