Metadata-Version: 2.1
Name: tuber
Version: 0.6.0
Summary: Finds project/repository root
Home-page: https://github.com/python-packaging/tuber/
Author: Tim Hatch
Author-email: tim@timhatch.com
License: MIT
Platform: UNKNOWN
Requires-Python: >=3.6
